optml/__init__.py
optml/data_reader.py
optml/initialization.py
optml/loss.py
optml/model.py
optml/optimizers.py
optml/trainer.py
opt_ml-1.0.5.dist-info/LICENSE
opt_ml-1.0.5.dist-info/METADATA
opt_ml-1.0.5.dist-info/WHEEL
opt_ml-1.0.5.dist-info/top_level.txt
opt_ml-1.0.5.dist-info/RECORD
