Metadata-Version: 2.1
Name: opt-ml
Version: 1.0.5
Summary: Optimization Tools for Research
Home-page: https://github.com/anishacharya/OptExp
Author: Anish Acharya
Author-email: anishacharya@utexas.edu
License: UNKNOWN
Platform: UNKNOWN
Classifier: Programming Language :: Python :: 3
Classifier: License :: OSI Approved :: MIT License
Classifier: Operating System :: OS Independent
Requires-Python: >=3.6
